bottle_tinyrpc/__init__.py
bottle_tinyrpc-0.1.0.dist-info/LICENSE
bottle_tinyrpc-0.1.0.dist-info/METADATA
bottle_tinyrpc-0.1.0.dist-info/WHEEL
bottle_tinyrpc-0.1.0.dist-info/top_level.txt
bottle_tinyrpc-0.1.0.dist-info/RECORD
